element_session/__init__.py
element_session/session_with_datetime.py
element_session/session_with_id.py
element_session/version.py
element_session/export/__init__.py
element_session/export/nwb.py
element_session-0.1.6.dist-info/LICENSE
element_session-0.1.6.dist-info/METADATA
element_session-0.1.6.dist-info/WHEEL
element_session-0.1.6.dist-info/top_level.txt
element_session-0.1.6.dist-info/RECORD
