Metadata-Version: 2.1
Name: element-session
Version: 0.1.6
Summary: DataJoint Element for Session Management
Home-page: https://github.com/datajoint/element-session
Author: DataJoint
Author-email: info@datajoint.com
License: MIT
Keywords: neuroscience session-management datajoint
Platform: UNKNOWN
License-File: LICENSE
Requires-Dist: datajoint >=0.13.0
